pyarchops_tinc/__init__.py
pyarchops_tinc/tinc.py
pyarchops_tinc-0.0.3.dist-info/AUTHORS.rst
pyarchops_tinc-0.0.3.dist-info/LICENSE
pyarchops_tinc-0.0.3.dist-info/METADATA
pyarchops_tinc-0.0.3.dist-info/WHEEL
pyarchops_tinc-0.0.3.dist-info/top_level.txt
pyarchops_tinc-0.0.3.dist-info/RECORD
