Metadata-Version: 2.1
Name: pyarchops-tinc
Version: 0.0.3
Summary: Install All tinc
Home-page: https://github.com/pyarchops/tinc
Author: Azul
Author-email: pyarchops@azulinho.com
License: MIT license
Keywords: pyarchops_tinc
Platform: UNKNOWN
Classifier: Development Status :: 2 - Pre-Alpha
Classifier: Intended Audience :: Developers
Classifier: License :: OSI Approved :: MIT License
Classifier: Natural Language :: English
Classifier: Programming Language :: Python :: 3.7
Requires-Dist: suitable
